django_libsass_compass_mixins/__init__.py
django_libsass_compass_mixins/static/_animate.scss
django_libsass_compass_mixins/static/_compass.scss
django_libsass_compass_mixins/static/_lemonade.scss
django_libsass_compass_mixins/static/animation/_animate.scss
django_libsass_compass_mixins/static/animation/_core.scss
django_libsass_compass_mixins/static/animation/_shared.scss
django_libsass_compass_mixins/static/animation/animate/_attention-seekers.scss
django_libsass_compass_mixins/static/animation/animate/_bouncing.scss
django_libsass_compass_mixins/static/animation/animate/_classes.scss
django_libsass_compass_mixins/static/animation/animate/_fading.scss
django_libsass_compass_mixins/static/animation/animate/_flippers.scss
django_libsass_compass_mixins/static/animation/animate/_lightspeed.scss
django_libsass_compass_mixins/static/animation/animate/_rotating.scss
django_libsass_compass_mixins/static/animation/animate/_specials.scss
django_libsass_compass_mixins/static/animation/animate/bouncing/_bouncing-entrances.scss
django_libsass_compass_mixins/static/animation/animate/bouncing/_bouncing-exits.scss
django_libsass_compass_mixins/static/animation/animate/fading/_fading-entrances.scss
django_libsass_compass_mixins/static/animation/animate/fading/_fading-exits.scss
django_libsass_compass_mixins/static/animation/animate/rotating/_rotating-entrances.scss
django_libsass_compass_mixins/static/animation/animate/rotating/_rotating-exits.scss
django_libsass_compass_mixins/static/compass/_css3.scss
django_libsass_compass_mixins/static/compass/_functions.scss
django_libsass_compass_mixins/static/compass/_layout.scss
django_libsass_compass_mixins/static/compass/_reset-legacy.scss
django_libsass_compass_mixins/static/compass/_reset.scss
django_libsass_compass_mixins/static/compass/_support.scss
django_libsass_compass_mixins/static/compass/_typography.scss
django_libsass_compass_mixins/static/compass/_utilities.scss
django_libsass_compass_mixins-0.12.10.dist-info/DESCRIPTION.rst
django_libsass_compass_mixins-0.12.10.dist-info/METADATA
django_libsass_compass_mixins-0.12.10.dist-info/RECORD
django_libsass_compass_mixins-0.12.10.dist-info/WHEEL
django_libsass_compass_mixins-0.12.10.dist-info/metadata.json
django_libsass_compass_mixins-0.12.10.dist-info/top_level.txt
